httpfluent/__init__.py
httpfluent/fluent.py
httpfluent/httpfluent.py
httpfluent/winssl.py
httpfluent-0.1.dist-info/LICENSE
httpfluent-0.1.dist-info/METADATA
httpfluent-0.1.dist-info/WHEEL
httpfluent-0.1.dist-info/entry_points.txt
httpfluent-0.1.dist-info/top_level.txt
httpfluent-0.1.dist-info/RECORD
