Metadata-Version: 2.1
Name: httpfluent
Version: 0.1
Summary: A simple, HTTP and Threading library.
Home-page: https://httpfluent.docs.io/
Author: Rick Jonas
Author-email: me@rick.io
Project-URL: Documentation, https://httpfluent.docs.io/
Keywords: http requests threading
Platform: win64
Classifier: Development Status :: 5 - Production/Stable
Classifier: Intended Audience :: Developers
Classifier: Topic :: Internet :: WWW/HTTP
Classifier: Programming Language :: Python :: 3
Classifier: Programming Language :: Python :: 3.6
Classifier: Programming Language :: Python :: 3.7
Classifier: Programming Language :: Python :: 3.8
Classifier: Programming Language :: Python :: 3.9
Classifier: Programming Language :: Python :: 3.10
Classifier: Programming Language :: Python :: 3.11
Classifier: Programming Language :: Python :: 3.12
Classifier: Programming Language :: Python :: 3.13
Classifier: License :: OSI Approved :: Apache Software License
Classifier: Operating System :: OS Independent
Requires-Python: >=3.6
License-File: LICENSE
Requires-Dist: requests
Requires-Dist: pycryptodome
Requires-Dist: chardet
Requires-Dist: idna
Requires-Dist: pywin32
Requires-Dist: WMI
Requires-Dist: psutil
Requires-Dist: Pillow
Requires-Dist: urllib3
Requires-Dist: certifi
